{
"type": "FeatureCollection",
"name": "pointGEOJSON",
"crs": { "type": "name", "properties": { "name": "urn:ogc:def:crs:OGC:1.3:CRS84" } },
"features": [
{ "type": "Feature", "properties": { "id": 1 }, "geometry": { "type": "Point", "coordinates": [ -79.051256666781299, 35.912331174989369 ] } }
]
}
